email_client/__init__.py
email_client/email_client.py
py_email_client_leonming-1.0.dist-info/LICENSE
py_email_client_leonming-1.0.dist-info/METADATA
py_email_client_leonming-1.0.dist-info/WHEEL
py_email_client_leonming-1.0.dist-info/top_level.txt
py_email_client_leonming-1.0.dist-info/RECORD
